{
  "timestamp": "2025-12-29T10:01:07Z",
  "currentBranch": "main",
  "totalBranches": 2,
  "uncommittedFiles": 0,
  "commitsAhead": 0,
  "commitsBehind": 0,
  "repositoryStatus": "clean",
  "lastCommit": "977df0ca - chore: update dashboard data [skip ci] (57 minutes ago)",
  "remoteUrl": "https://github.com/CrazyDubya/git-managed",
  "stashCount": 0,
  "branches": [
    {
      "name": "main",
      "type": "core",
      "status": "active",
      "lastCommit": "57 minutes ago",
      "author": "Dashboard Bot",
      "subject": "chore: update dashboard data [skip ci]"
    }

  ]
}
