{
  "timestamp": "2025-12-03T11:01:11Z",
  "recentCommits": [
    {
      "hash": "761f10c3",
      "subject": "chore: update dashboard data [skip ci]",
      "author": "Dashboard Bot",
      "date": "60 minutes ago"
    }
,
    {
      "hash": "7bf52891",
      "subject": "chore: update dashboard data [skip ci]",
      "author": "Dashboard Bot",
      "date": "2 hours ago"
    }
,
    {
      "hash": "a1aef358",
      "subject": "chore: update dashboard data [skip ci]",
      "author": "Dashboard Bot",
      "date": "20 hours ago"
    }
,
    {
      "hash": "784aeed2",
      "subject": "chore: update dashboard data [skip ci]",
      "author": "Dashboard Bot",
      "date": "21 hours ago"
    }
,
    {
      "hash": "f75842d7",
      "subject": "chore: update dashboard data [skip ci]",
      "author": "Dashboard Bot",
      "date": "22 hours ago"
    }
,
    {
      "hash": "37e1f2a3",
      "subject": "chore: update dashboard data [skip ci]",
      "author": "Dashboard Bot",
      "date": "23 hours ago"
    }
,
    {
      "hash": "fdc48bf2",
      "subject": "chore: update dashboard data [skip ci]",
      "author": "Dashboard Bot",
      "date": "24 hours ago"
    }
,
    {
      "hash": "fa5d7bd1",
      "subject": "chore: update dashboard data [skip ci]",
      "author": "Dashboard Bot",
      "date": "25 hours ago"
    }
,
    {
      "hash": "8aecac48",
      "subject": "chore: update dashboard data [skip ci]",
      "author": "Dashboard Bot",
      "date": "26 hours ago"
    }
,
    {
      "hash": "95c11f98",
      "subject": "chore: update dashboard data [skip ci]",
      "author": "Dashboard Bot",
      "date": "2 days ago"
    }

  ]
}
