{
  "timestamp": "2025-08-12T16:08:33Z",
  "recentCommits": [
    {
      "hash": "00a52ea",
      "subject": "chore: update dashboard data [skip ci]",
      "author": "Dashboard Bot",
      "date": "18 minutes ago"
    }
,
    {
      "hash": "d98ee8e",
      "subject": "chore: update dashboard data [skip ci]",
      "author": "Dashboard Bot",
      "date": "30 minutes ago"
    }
,
    {
      "hash": "dabdedf",
      "subject": "chore: update dashboard data [skip ci]",
      "author": "Dashboard Bot",
      "date": "43 minutes ago"
    }
,
    {
      "hash": "1c10617",
      "subject": "chore: update dashboard data [skip ci]",
      "author": "Dashboard Bot",
      "date": "61 minutes ago"
    }
,
    {
      "hash": "f7d5ca2",
      "subject": "chore: update dashboard data [skip ci]",
      "author": "Dashboard Bot",
      "date": "77 minutes ago"
    }
,
    {
      "hash": "c61b591",
      "subject": "chore: update dashboard data [skip ci]",
      "author": "Dashboard Bot",
      "date": "89 minutes ago"
    }
,
    {
      "hash": "f0eb5ab",
      "subject": "chore: update dashboard data [skip ci]",
      "author": "Dashboard Bot",
      "date": "2 hours ago"
    }
,
    {
      "hash": "8850825",
      "subject": "chore: update dashboard data [skip ci]",
      "author": "Dashboard Bot",
      "date": "2 hours ago"
    }
,
    {
      "hash": "042c3a9",
      "subject": "chore: update dashboard data [skip ci]",
      "author": "Dashboard Bot",
      "date": "2 hours ago"
    }
,
    {
      "hash": "7da5330",
      "subject": "chore: update dashboard data [skip ci]",
      "author": "Dashboard Bot",
      "date": "2 hours ago"
    }

  ]
}
