{
  "timestamp": "2025-09-23T11:49:20Z",
  "recentCommits": [
    {
      "hash": "eeb487c8",
      "subject": "chore: update dashboard data [skip ci]",
      "author": "Dashboard Bot",
      "date": "15 minutes ago"
    }
,
    {
      "hash": "3348297f",
      "subject": "chore: update dashboard data [skip ci]",
      "author": "Dashboard Bot",
      "date": "27 minutes ago"
    }
,
    {
      "hash": "0d79b2d2",
      "subject": "chore: update dashboard data [skip ci]",
      "author": "Dashboard Bot",
      "date": "43 minutes ago"
    }
,
    {
      "hash": "4e7f2e94",
      "subject": "chore: update dashboard data [skip ci]",
      "author": "Dashboard Bot",
      "date": "60 minutes ago"
    }
,
    {
      "hash": "abe78267",
      "subject": "chore: update dashboard data [skip ci]",
      "author": "Dashboard Bot",
      "date": "71 minutes ago"
    }
,
    {
      "hash": "bcf31116",
      "subject": "chore: update dashboard data [skip ci]",
      "author": "Dashboard Bot",
      "date": "84 minutes ago"
    }
,
    {
      "hash": "b1d172fd",
      "subject": "chore: update dashboard data [skip ci]",
      "author": "Dashboard Bot",
      "date": "2 hours ago"
    }
,
    {
      "hash": "ba63ad13",
      "subject": "chore: update dashboard data [skip ci]",
      "author": "Dashboard Bot",
      "date": "2 hours ago"
    }
,
    {
      "hash": "15f0dd34",
      "subject": "chore: update dashboard data [skip ci]",
      "author": "Dashboard Bot",
      "date": "2 hours ago"
    }
,
    {
      "hash": "92c28f37",
      "subject": "chore: update dashboard data [skip ci]",
      "author": "Dashboard Bot",
      "date": "2 hours ago"
    }

  ]
}
