{
  "timestamp": "2025-10-10T18:51:39Z",
  "recentCommits": [
    {
      "hash": "b067c43d",
      "subject": "chore: update dashboard data [skip ci]",
      "author": "Dashboard Bot",
      "date": "10 minutes ago"
    }
,
    {
      "hash": "589eda7d",
      "subject": "chore: update dashboard data [skip ci]",
      "author": "Dashboard Bot",
      "date": "25 minutes ago"
    }
,
    {
      "hash": "41a0eeaa",
      "subject": "chore: update dashboard data [skip ci]",
      "author": "Dashboard Bot",
      "date": "42 minutes ago"
    }
,
    {
      "hash": "fc91ac43",
      "subject": "chore: update dashboard data [skip ci]",
      "author": "Dashboard Bot",
      "date": "63 minutes ago"
    }
,
    {
      "hash": "2cefc9a3",
      "subject": "chore: update dashboard data [skip ci]",
      "author": "Dashboard Bot",
      "date": "76 minutes ago"
    }
,
    {
      "hash": "2d982c44",
      "subject": "chore: update dashboard data [skip ci]",
      "author": "Dashboard Bot",
      "date": "88 minutes ago"
    }
,
    {
      "hash": "8d27a812",
      "subject": "chore: update dashboard data [skip ci]",
      "author": "Dashboard Bot",
      "date": "2 hours ago"
    }
,
    {
      "hash": "803d9be3",
      "subject": "chore: update dashboard data [skip ci]",
      "author": "Dashboard Bot",
      "date": "2 hours ago"
    }
,
    {
      "hash": "84b4bc21",
      "subject": "chore: update dashboard data [skip ci]",
      "author": "Dashboard Bot",
      "date": "2 hours ago"
    }
,
    {
      "hash": "ace746b3",
      "subject": "chore: update dashboard data [skip ci]",
      "author": "Dashboard Bot",
      "date": "2 hours ago"
    }

  ]
}
