{
  "timestamp": "2025-10-09T17:07:00Z",
  "recentCommits": [
    {
      "hash": "85d64b06",
      "subject": "chore: update dashboard data [skip ci]",
      "author": "Dashboard Bot",
      "date": "14 minutes ago"
    }
,
    {
      "hash": "40799132",
      "subject": "chore: update dashboard data [skip ci]",
      "author": "Dashboard Bot",
      "date": "25 minutes ago"
    }
,
    {
      "hash": "47786424",
      "subject": "chore: update dashboard data [skip ci]",
      "author": "Dashboard Bot",
      "date": "41 minutes ago"
    }
,
    {
      "hash": "eccc2baf",
      "subject": "chore: update dashboard data [skip ci]",
      "author": "Dashboard Bot",
      "date": "58 minutes ago"
    }
,
    {
      "hash": "d4c262cd",
      "subject": "chore: update dashboard data [skip ci]",
      "author": "Dashboard Bot",
      "date": "74 minutes ago"
    }
,
    {
      "hash": "e1b4ece5",
      "subject": "chore: update dashboard data [skip ci]",
      "author": "Dashboard Bot",
      "date": "2 hours ago"
    }
,
    {
      "hash": "d16f3435",
      "subject": "chore: update dashboard data [skip ci]",
      "author": "Dashboard Bot",
      "date": "2 hours ago"
    }
,
    {
      "hash": "10c67de3",
      "subject": "chore: update dashboard data [skip ci]",
      "author": "Dashboard Bot",
      "date": "2 hours ago"
    }
,
    {
      "hash": "fb47d13c",
      "subject": "chore: update dashboard data [skip ci]",
      "author": "Dashboard Bot",
      "date": "2 hours ago"
    }
,
    {
      "hash": "118977b2",
      "subject": "chore: update dashboard data [skip ci]",
      "author": "Dashboard Bot",
      "date": "3 hours ago"
    }

  ]
}
