{
  "timestamp": "2025-09-10T16:50:51Z",
  "recentCommits": [
    {
      "hash": "5f78479",
      "subject": "chore: update dashboard data [skip ci]",
      "author": "Dashboard Bot",
      "date": "11 minutes ago"
    }
,
    {
      "hash": "254a494",
      "subject": "chore: update dashboard data [skip ci]",
      "author": "Dashboard Bot",
      "date": "25 minutes ago"
    }
,
    {
      "hash": "7351092",
      "subject": "chore: update dashboard data [skip ci]",
      "author": "Dashboard Bot",
      "date": "42 minutes ago"
    }
,
    {
      "hash": "d3020b4",
      "subject": "chore: update dashboard data [skip ci]",
      "author": "Dashboard Bot",
      "date": "62 minutes ago"
    }
,
    {
      "hash": "7d1aa8c",
      "subject": "chore: update dashboard data [skip ci]",
      "author": "Dashboard Bot",
      "date": "75 minutes ago"
    }
,
    {
      "hash": "3801e98",
      "subject": "chore: update dashboard data [skip ci]",
      "author": "Dashboard Bot",
      "date": "86 minutes ago"
    }
,
    {
      "hash": "6bcb1aa",
      "subject": "chore: update dashboard data [skip ci]",
      "author": "Dashboard Bot",
      "date": "2 hours ago"
    }
,
    {
      "hash": "942dcaf",
      "subject": "chore: update dashboard data [skip ci]",
      "author": "Dashboard Bot",
      "date": "2 hours ago"
    }
,
    {
      "hash": "d7092ab",
      "subject": "chore: update dashboard data [skip ci]",
      "author": "Dashboard Bot",
      "date": "2 hours ago"
    }
,
    {
      "hash": "93ca139",
      "subject": "chore: update dashboard data [skip ci]",
      "author": "Dashboard Bot",
      "date": "2 hours ago"
    }

  ]
}
