{
  "timestamp": "2025-08-21T16:25:32Z",
  "recentCommits": [
    {
      "hash": "7922af9",
      "subject": "chore: update dashboard data [skip ci]",
      "author": "Dashboard Bot",
      "date": "18 minutes ago"
    }
,
    {
      "hash": "5351cab",
      "subject": "chore: update dashboard data [skip ci]",
      "author": "Dashboard Bot",
      "date": "36 minutes ago"
    }
,
    {
      "hash": "9b73a7b",
      "subject": "chore: update dashboard data [skip ci]",
      "author": "Dashboard Bot",
      "date": "48 minutes ago"
    }
,
    {
      "hash": "5f1c97e",
      "subject": "chore: update dashboard data [skip ci]",
      "author": "Dashboard Bot",
      "date": "61 minutes ago"
    }
,
    {
      "hash": "52cdd93",
      "subject": "chore: update dashboard data [skip ci]",
      "author": "Dashboard Bot",
      "date": "78 minutes ago"
    }
,
    {
      "hash": "a5301e3",
      "subject": "chore: update dashboard data [skip ci]",
      "author": "Dashboard Bot",
      "date": "2 hours ago"
    }
,
    {
      "hash": "a9a0b66",
      "subject": "chore: update dashboard data [skip ci]",
      "author": "Dashboard Bot",
      "date": "2 hours ago"
    }
,
    {
      "hash": "b51c6c3",
      "subject": "chore: update dashboard data [skip ci]",
      "author": "Dashboard Bot",
      "date": "2 hours ago"
    }
,
    {
      "hash": "a0a4bf3",
      "subject": "chore: update dashboard data [skip ci]",
      "author": "Dashboard Bot",
      "date": "2 hours ago"
    }
,
    {
      "hash": "53abaf6",
      "subject": "chore: update dashboard data [skip ci]",
      "author": "Dashboard Bot",
      "date": "3 hours ago"
    }

  ]
}
