{
  "timestamp": "2025-10-14T17:49:11Z",
  "recentCommits": [
    {
      "hash": "12799387",
      "subject": "chore: update dashboard data [skip ci]",
      "author": "Dashboard Bot",
      "date": "14 minutes ago"
    }
,
    {
      "hash": "aed05b6d",
      "subject": "chore: update dashboard data [skip ci]",
      "author": "Dashboard Bot",
      "date": "26 minutes ago"
    }
,
    {
      "hash": "14e42325",
      "subject": "chore: update dashboard data [skip ci]",
      "author": "Dashboard Bot",
      "date": "42 minutes ago"
    }
,
    {
      "hash": "d54c60db",
      "subject": "chore: update dashboard data [skip ci]",
      "author": "Dashboard Bot",
      "date": "57 minutes ago"
    }
,
    {
      "hash": "15479b18",
      "subject": "chore: update dashboard data [skip ci]",
      "author": "Dashboard Bot",
      "date": "68 minutes ago"
    }
,
    {
      "hash": "61a6b3a8",
      "subject": "chore: update dashboard data [skip ci]",
      "author": "Dashboard Bot",
      "date": "84 minutes ago"
    }
,
    {
      "hash": "e8dbdb56",
      "subject": "chore: update dashboard data [skip ci]",
      "author": "Dashboard Bot",
      "date": "2 hours ago"
    }
,
    {
      "hash": "a4b157f8",
      "subject": "chore: update dashboard data [skip ci]",
      "author": "Dashboard Bot",
      "date": "2 hours ago"
    }
,
    {
      "hash": "3fb79e6d",
      "subject": "chore: update dashboard data [skip ci]",
      "author": "Dashboard Bot",
      "date": "2 hours ago"
    }
,
    {
      "hash": "5fdc7de8",
      "subject": "chore: update dashboard data [skip ci]",
      "author": "Dashboard Bot",
      "date": "2 hours ago"
    }

  ]
}
