{
  "timestamp": "2025-10-27T11:49:13Z",
  "recentCommits": [
    {
      "hash": "ad97362a",
      "subject": "chore: update dashboard data [skip ci]",
      "author": "Dashboard Bot",
      "date": "14 minutes ago"
    }
,
    {
      "hash": "036edfa9",
      "subject": "chore: update dashboard data [skip ci]",
      "author": "Dashboard Bot",
      "date": "25 minutes ago"
    }
,
    {
      "hash": "1c7b0d2d",
      "subject": "chore: update dashboard data [skip ci]",
      "author": "Dashboard Bot",
      "date": "42 minutes ago"
    }
,
    {
      "hash": "acc29dee",
      "subject": "chore: update dashboard data [skip ci]",
      "author": "Dashboard Bot",
      "date": "58 minutes ago"
    }
,
    {
      "hash": "37e5da33",
      "subject": "chore: update dashboard data [skip ci]",
      "author": "Dashboard Bot",
      "date": "69 minutes ago"
    }
,
    {
      "hash": "6536da48",
      "subject": "chore: update dashboard data [skip ci]",
      "author": "Dashboard Bot",
      "date": "84 minutes ago"
    }
,
    {
      "hash": "5ebcc775",
      "subject": "chore: update dashboard data [skip ci]",
      "author": "Dashboard Bot",
      "date": "2 hours ago"
    }
,
    {
      "hash": "33052f74",
      "subject": "chore: update dashboard data [skip ci]",
      "author": "Dashboard Bot",
      "date": "2 hours ago"
    }
,
    {
      "hash": "898a8ef2",
      "subject": "chore: update dashboard data [skip ci]",
      "author": "Dashboard Bot",
      "date": "2 hours ago"
    }
,
    {
      "hash": "9ffff880",
      "subject": "chore: update dashboard data [skip ci]",
      "author": "Dashboard Bot",
      "date": "2 hours ago"
    }

  ]
}
