{
  "timestamp": "2025-09-18T10:49:05Z",
  "recentCommits": [
    {
      "hash": "f57a2dfb",
      "subject": "chore: update dashboard data [skip ci]",
      "author": "Dashboard Bot",
      "date": "12 minutes ago"
    }
,
    {
      "hash": "3b22542c",
      "subject": "chore: update dashboard data [skip ci]",
      "author": "Dashboard Bot",
      "date": "24 minutes ago"
    }
,
    {
      "hash": "f73aaa2d",
      "subject": "chore: update dashboard data [skip ci]",
      "author": "Dashboard Bot",
      "date": "42 minutes ago"
    }
,
    {
      "hash": "fd04026b",
      "subject": "chore: update dashboard data [skip ci]",
      "author": "Dashboard Bot",
      "date": "60 minutes ago"
    }
,
    {
      "hash": "6a53879b",
      "subject": "chore: update dashboard data [skip ci]",
      "author": "Dashboard Bot",
      "date": "73 minutes ago"
    }
,
    {
      "hash": "ba9c442d",
      "subject": "chore: update dashboard data [skip ci]",
      "author": "Dashboard Bot",
      "date": "84 minutes ago"
    }
,
    {
      "hash": "4206347b",
      "subject": "chore: update dashboard data [skip ci]",
      "author": "Dashboard Bot",
      "date": "2 hours ago"
    }
,
    {
      "hash": "838aeadc",
      "subject": "chore: update dashboard data [skip ci]",
      "author": "Dashboard Bot",
      "date": "16 hours ago"
    }
,
    {
      "hash": "a95ee594",
      "subject": "chore: update dashboard data [skip ci]",
      "author": "Dashboard Bot",
      "date": "16 hours ago"
    }
,
    {
      "hash": "9fa74dcc",
      "subject": "chore: update dashboard data [skip ci]",
      "author": "Dashboard Bot",
      "date": "16 hours ago"
    }

  ]
}
